Workbook

Sheet Assumptions
A1: Assumption | B1: Unit | C1: 2025 Proj | D1: 2026 Proj | E1: 2027 Proj
A2: Active Scenario Toggle | B2: [1=Base] | C2: 1 | D2: 1 | E2: 1
A3: Contract Volume Growth | B3: % | C3: 0.08 | D3: 0.1 | E3: 0.12
A4: Construction COGS Margin | B4: % | C4: 0.7 | D4: 0.68 | E4: 0.68
A5: Tax Rate | B5: % | C5: 0.29 | D5: 0.29 | E5: 0.29
A6: WACC (Discount Rate) | B6: % | C6: 0.15 | D6: 0.15 | E6: 0.15
A7: Terminal Growth Rate | B7: % | C7: 0.03 | D7: 0.03 | E7: 0.03

Sheet Model
A1: Financials (In 000s) | B1: 2024 Actual | C1: 2025 Proj | D1: 2026 Proj | E1: 2027 Proj
A2: INCOME STATEMENT
A3: Revenue | B3: 100000 | C3: =B3*(1+Assumptions!C3) -> 108000 | D3: =C3*(1+Assumptions!D3) -> 118800 | E3: =D3*(1+Assumptions!E3) -> 133056
A4: COGS (Labor & Materials) | B4: -72000 | C4: =-C3*Assumptions!C4 -> -75600 | D4: =-D3*Assumptions!D4 -> -80784 | E4: =-E3*Assumptions!E4 -> -90478.08
A5: Gross Profit | B5: =SUM(B3:B4) -> 28000 | C5: =SUM(C3:C4) -> 32400 | D5: =SUM(D3:D4) -> 38016 | E5: =SUM(E3:E4) -> 42577.92
A6: SG&A (C-5 Admin & Licensing) | B6: -15000 | C6: -16000 | D6: -17500 | E6: -19000
A7: EBITDA | B7: =SUM(B5:B6) -> 13000 | C7: =SUM(C5:C6) -> 16400 | D7: =SUM(D5:D6) -> 20516 | E7: =SUM(E5:E6) -> 23577.92
A8: Depreciation | B8: -5000 | C8: -5500 | D8: -6000 | E8: -6000
A9: EBIT | B9: =SUM(B7:B8) -> 8000 | C9: =SUM(C7:C8) -> 10900 | D9: =SUM(D7:D8) -> 14516 | E9: =SUM(E7:E8) -> 17577.92
A10: Interest Expense | B10: -2000 | C10: -1800 | D10: -1500 | E10: -1000
A11: EBT | B11: =SUM(B9:B10) -> 6000 | C11: =SUM(C9:C10) -> 9100 | D11: =SUM(D9:D10) -> 13016 | E11: =SUM(E9:E10) -> 16577.92
A12: Taxes | B12: =B11*-0.29 -> -1740 | C12: =-C11*Assumptions!C5 -> -2639 | D12: =-D11*Assumptions!D5 -> -3774.64 | E12: =-E11*Assumptions!E5 -> -4807.5968
A13: Net Income | B13: =SUM(B11:B12) -> 4260 | C13: =SUM(C11:C12) -> 6461 | D13: =SUM(D11:D12) -> 9241.36 | E13: =SUM(E11:E12) -> 11770.323
A15: DCF VALUATION ENGINE
A16: EBIT | C16: =C9 -> 10900 | D16: =D9 -> 14516 | E16: =E9 -> 17577.92
A17: Less: Taxes on EBIT | C17: =C16*-Assumptions!C5 -> -3161 | D17: =D16*-Assumptions!D5 -> -4209.64 | E17: =E16*-Assumptions!E5 -> -5097.5968
A18: NOPAT | C18: =SUM(C16:C17) -> 7739 | D18: =SUM(D16:D17) -> 10306.36 | E18: =SUM(E16:E17) -> 12480.323
A19: Add: Depreciation | C19: =-C8 -> 5500 | D19: =-D8 -> 6000 | E19: =-E8 -> 6000
A20: Less: Heavy Machinery CAPEX | C20: -8000 | D20: -9000 | E20: -5000
A21: Less: Change in NWC | C21: -1500 | D21: -2000 | E21: -2500
A22: Unlevered Free Cash Flow (UFCF) | C22: =SUM(C18:C21) -> 3739 | D22: =SUM(D18:D21) -> 5306.36 | E22: =SUM(E18:E21) -> 10980.323
A23: Discount Factor | C23: =1/((1+Assumptions!C6)^1) -> 0.86956522 | D23: =1/((1+Assumptions!C6)^2) -> 0.75614367 | E23: =1/((1+Assumptions!C6)^3) -> 0.65751623
A24: Present Value of UFCF | C24: =C22*C23 -> 3251.3043 | D24: =D22*D23 -> 4012.3705 | E24: =E22*E23 -> 7219.7407
A26: ENTERPRISE VALUE ROLLUP
A27: Sum of PV of UFCF | B27: =SUM(C24:E24) -> 14483.416
A28: Terminal Value (Gordon Growth) | B28: =(E23*(1+Assumptions!C7))/(Assumptions!C6-Assumptions!C7) -> 5.643681
A29: PV of Terminal Value | B29: =B28*E23 -> 3.7108119
A30: Implied Enterprise Value | B30: =B27+B29 -> 14487.126
A31: Less: Total Debt | B31: -15000
A32: Add: Cash | B32: 8000
A33: Implied Equity Value | B33: =B30+B31+B32 -> 7487.1264
